.DS_Store
fcs-0.6.data/scripts/fcs
fcs-0.6.dist-info/METADATA
fcs-0.6.dist-info/RECORD
fcs-0.6.dist-info/WHEEL
fcs-0.6.dist-info/top_level.txt
fcs_pkg/__init__.py
fcs_pkg/rings/1.mp3
fcs_pkg/rings/10.mp3
fcs_pkg/rings/11.mp3
fcs_pkg/rings/12.mp3
fcs_pkg/rings/13.mp3
fcs_pkg/rings/14.mp3
fcs_pkg/rings/15.mp3
fcs_pkg/rings/16.mp3
fcs_pkg/rings/17.mp3
fcs_pkg/rings/18.mp3
fcs_pkg/rings/19.mp3
fcs_pkg/rings/2.mp3
fcs_pkg/rings/3.mp3
fcs_pkg/rings/4.mp3
fcs_pkg/rings/5.mp3
fcs_pkg/rings/6.mp3
fcs_pkg/rings/7.mp3
fcs_pkg/rings/8.mp3
fcs_pkg/rings/9.mp3
fcs_pkg/rings/__init__.py
