Metadata-Version: 2.1
Name: fcs
Version: 0.6
Summary: A simple, powerful, and open-source time tracker from the command line
Home-page: https://github.com/ammar1y/Focus-Phase
Author: Ammar Alyousfi
Author-email: ammar5656@gmail.com
License: UNKNOWN
Platform: UNKNOWN
Classifier: Programming Language :: Python :: 3
Classifier: License :: OSI Approved :: MIT License
Classifier: Operating System :: OS Independent
Requires-Dist: pandas
Requires-Dist: matplotlib
